[{"source": "https://www.youtube.com/feeds/videos.xml?channel_id=UCLLO-H4NQXNa_DhUv-rqN9g", "title": "Dlaczego jeszcze nie zagrali\u015bcie w Ghostrunnera 2?", "description": "Ghostrunner 2 posz\u0142o w zupe\u0142nie innym kierunku, ni\u017c Ghostrunner 1. I bardzo dobrze. Tylko czemu tak ma\u0142o os\u00f3b to doceni\u0142o?\n\nWbijajcie na nasz nowy Instagram: https://instagram.com/cdaction\n\nKoniecznie zobacz nas w innych miejscach:\n\nStrona :: https://cdaction.pl/\nSklep :: https://sklep.cdaction.pl/\nInstagram :: https://instagram.com/cdaction\nFacebook :: http://fb.me/CDAction/\nTwitter :: https://twitter.com/cdaction\nDiscord CD-Action :: https://discord.gg/9Aqf3Cjcxx\nKontakt :: youtube@cdaction.pl\n\nProwadzenie i scenariusz: Krzysztof \u201eBastian\u201d Freudenberger (http://twitter.com/BastianCDA)\n\nMonta\u017c: Mateusz Pietrasiak", "link": "https://www.youtube.com/watch?v=zo6wq8zNg_s", "date_published": "2023-11-18T09:08:22+00:00", "permanent": false, "bookmarked": false, "dead": false, "artist": "CD-Action - YouTube", "album": "CD-Action - YouTube", "user": null, "language": "pl", "thumbnail": "https://i3.ytimg.com/vi/zo6wq8zNg_s/hqdefault.jpg", "age": null, "page_rating_contents": 0, "page_rating_votes": 0, "page_rating_visits": 1, "page_rating": 0, "tags": [], "comments": [], "vote": 0}]