[{"age": null, "album": "", "artist": null, "bookmarked": false, "comments": [], "date_published": "2024-08-24T12:24:00+00:00", "description": "Dynamic proxy is a powerful concept in Java and Spring that allows for the creation of proxy objects at runtime rather than compile-time.", "id": 1053551, "language": "en-us", "link": "https://www.codeproject.com/Articles/5387291/Dynamic-Proxy-in-Spring-A-Comprehensive-Guide-with", "manual_status_code": 0, "page_rating": 27, "page_rating_contents": 86, "page_rating_visits": 0, "page_rating_votes": 0, "permanent": false, "source": "https://www.codeproject.com/WebServices/ArticleRSS.aspx?cat=1", "source_obj__id": 73, "status_code": 0, "tags": [], "thumbnail": null, "title": "Dynamic Proxy in Spring: A Comprehensive Guide with Examples and Demos", "user": null, "vote": 0}, {"age": null, "album": "", "artist": null, "bookmarked": false, "comments": [], "date_published": "2024-08-24T11:23:00+00:00", "description": "Java Database Connectivity (JDBC) drivers are a critical component for Java developers, enabling seamless interaction between Java applications and databases. Choosing the right type of JDBC driver can significantly impact the performance, portability, and security of your applications.", "id": 1053552, "language": "en-us", "link": "https://www.codeproject.com/Articles/5387283/Reasons-Why-Understanding-JDBC-Driver-Types-Is-Cru", "manual_status_code": 0, "page_rating": 27, "page_rating_contents": 86, "page_rating_visits": 0, "page_rating_votes": 0, "permanent": false, "source": "https://www.codeproject.com/WebServices/ArticleRSS.aspx?cat=1", "source_obj__id": 73, "status_code": 0, "tags": [], "thumbnail": null, "title": "Reasons Why Understanding JDBC Driver Types Is Crucial for Java Developers", "user": null, "vote": 0}, {"age": null, "album": "", "artist": null, "bookmarked": false, "comments": [], "date_published": "2024-08-24T10:54:00+00:00", "description": "This article describes using the ZXing Library to generate and read QR codes.", "id": 1053553, "language": "en-us", "link": "https://www.codeproject.com/Articles/5387296/Generating-and-Reading-QR-Codes-in-a-Java-Applicat", "manual_status_code": 0, "page_rating": 27, "page_rating_contents": 86, "page_rating_visits": 0, "page_rating_votes": 0, "permanent": false, "source": "https://www.codeproject.com/WebServices/ArticleRSS.aspx?cat=1", "source_obj__id": 73, "status_code": 0, "tags": [], "thumbnail": null, "title": "Generating and Reading QR Codes in a Java Application using ZXing Library.", "user": null, "vote": 0}]