[
    {
        "age": null,
        "album": "",
        "author": null,
        "bookmarked": false,
        "comments": [],
        "date_published": "2024-12-02T18:09:08+00:00",
        "description": "&quot;Who&apos;s the Boss&quot; star, Danny Pintauro, shared with his Instagram followers he was involved in a scooter accident on Thanksgiving, which landed him in the hospital a few days later.",
        "id": 1630110,
        "language": "en-US",
        "link": "https://www.foxnews.com/entertainment/whos-boss-star-hospitalized-emergency-surgery-thanksgiving-accident",
        "manual_status_code": 0,
        "page_rating": 27,
        "page_rating_contents": 86,
        "page_rating_visits": 0,
        "page_rating_votes": 0,
        "permanent": false,
        "source__id": 120,
        "source_url": "https://moxie.foxnews.com/google-publisher/latest.xml",
        "status_code": 0,
        "tags": [],
        "thumbnail": "https://a57.foxnews.com/static.foxnews.com/foxnews.com/content/uploads/2024/12/931/523/danny-pintauro-whos-the-boss.jpg?ve=1&tl=1",
        "title": "'Who's the Boss' star hospitalized for emergency surgery after Thanksgiving accident",
        "vote": 0
    },
    {
        "age": null,
        "album": "",
        "author": null,
        "bookmarked": false,
        "comments": [],
        "date_published": "2024-12-02T18:07:36+00:00",
        "description": "California state lawmaker Isaac Bryan wants to give priority admission at state public universities to the descendants of slaves to right past wrongs.",
        "id": 1630111,
        "language": "en-US",
        "link": "https://www.foxnews.com/us/california-lawmaker-says-bill-give-admission-priority-public-university-descendants-slaves",
        "manual_status_code": 0,
        "page_rating": 27,
        "page_rating_contents": 86,
        "page_rating_visits": 0,
        "page_rating_votes": 0,
        "permanent": false,
        "source__id": 120,
        "source_url": "https://moxie.foxnews.com/google-publisher/latest.xml",
        "status_code": 0,
        "tags": [],
        "thumbnail": "https://a57.foxnews.com/static.foxnews.com/foxnews.com/content/uploads/2024/12/931/523/bryan.jpg?ve=1&tl=1",
        "title": "California lawmaker says bill would give admission priority at public university to descendants of slaves",
        "vote": 0
    },
    {
        "age": null,
        "album": "",
        "author": null,
        "bookmarked": false,
        "comments": [],
        "date_published": "2024-12-02T18:00:00+00:00",
        "description": "Edison, New Jersey resident Joel Bassoff was escorted out of a town council meeting for waving an American flag in protest of a new rule that bans such items.",
        "id": 1630112,
        "language": "en-US",
        "link": "https://www.foxnews.com/media/new-jersey-lawyer-ejected-from-town-council-meeting-waving-american-flag-protest-disgusting-new-ban",
        "manual_status_code": 0,
        "page_rating": 27,
        "page_rating_contents": 86,
        "page_rating_visits": 0,
        "page_rating_votes": 0,
        "permanent": false,
        "source__id": 120,
        "source_url": "https://moxie.foxnews.com/google-publisher/latest.xml",
        "status_code": 0,
        "tags": [],
        "thumbnail": "https://a57.foxnews.com/static.foxnews.com/foxnews.com/content/uploads/2021/06/931/523/iStock-1128969702.jpg?ve=1&tl=1",
        "title": "New Jersey lawyer ejected from town council meeting for waving American flag to protest 'disgusting' new ban",
        "vote": 0
    },
    {
        "age": null,
        "album": "",
        "author": null,
        "bookmarked": false,
        "comments": [],
        "date_published": "2024-12-02T17:54:58+00:00",
        "description": "Daniel Craig didn&apos;t mince words while recalling his least favorite James Bond film, and why a writers strike made the spy thriller so difficult to shoot.",
        "id": 1630113,
        "language": "en-US",
        "link": "https://www.foxnews.com/entertainment/daniel-craig-criticizes-james-bond-film-nightmare-zero-storytelling",
        "manual_status_code": 0,
        "page_rating": 27,
        "page_rating_contents": 86,
        "page_rating_visits": 0,
        "page_rating_votes": 0,
        "permanent": false,
        "source__id": 120,
        "source_url": "https://moxie.foxnews.com/google-publisher/latest.xml",
        "status_code": 0,
        "tags": [],
        "thumbnail": "https://a57.foxnews.com/static.foxnews.com/foxnews.com/content/uploads/2024/12/931/523/daniel-craig-quantum-of-solace.jpg?ve=1&tl=1",
        "title": "Daniel Craig criticizes James Bond film as a 'nightmare' with zero storytelling",
        "vote": 0
    },
    {
        "age": null,
        "album": "",
        "author": null,
        "bookmarked": false,
        "comments": [],
        "date_published": "2024-12-02T17:39:38+00:00",
        "description": "Kate Winslet revealed she had a face-to-face with an interviewer who had shamed the actress over her body. The &quot;Titanic&quot; star faced intense scrutiny over her appearance as a young star.",
        "id": 1630114,
        "language": "en-US",
        "link": "https://www.foxnews.com/entertainment/kate-winslet-confronted-fat-shaming-critic-emotional-face-off",
        "manual_status_code": 0,
        "page_rating": 27,
        "page_rating_contents": 86,
        "page_rating_visits": 0,
        "page_rating_votes": 0,
        "permanent": false,
        "source__id": 120,
        "source_url": "https://moxie.foxnews.com/google-publisher/latest.xml",
        "status_code": 0,
        "tags": [],
        "thumbnail": "https://a57.foxnews.com/static.foxnews.com/foxnews.com/content/uploads/2024/12/931/523/kate_winslet_titanic_premiere.jpg?ve=1&tl=1",
        "title": "Kate Winslet confronted fat-shaming critic in emotional face-off",
        "vote": 0
    },
    {
        "age": null,
        "album": "",
        "author": null,
        "bookmarked": false,
        "comments": [],
        "date_published": "2024-12-02T17:39:16+00:00",
        "description": "As the San Francisco 49ers confirmed Christian McCaffrey suffered a likely season-ending injury, his backup, Jordan Mason, landed on IR with a high-ankle sprain.",
        "id": 1630115,
        "language": "en-US",
        "link": "https://www.foxnews.com/sports/christian-mccaffreys-backup-lands-ir-49ers-lose-2-running-backs-rollercoaster-season",
        "manual_status_code": 0,
        "page_rating": 27,
        "page_rating_contents": 86,
        "page_rating_visits": 0,
        "page_rating_votes": 0,
        "permanent": false,
        "source__id": 120,
        "source_url": "https://moxie.foxnews.com/google-publisher/latest.xml",
        "status_code": 0,
        "tags": [],
        "thumbnail": "https://a57.foxnews.com/static.foxnews.com/foxnews.com/content/uploads/2024/12/931/523/jordan-mason-.jpg?ve=1&tl=1",
        "title": "Christian McCaffrey\u2019s backup lands on IR as 49ers lose 2 running backs in roller-coaster season",
        "vote": 0
    },
    {
        "age": null,
        "album": "",
        "author": null,
        "bookmarked": false,
        "comments": [],
        "date_published": "2024-12-02T17:24:34+00:00",
        "description": "Russian tourist Kamilla Beliatskaya died on Friday after she was swept away by a large wave while doing yoga on a rock in Koh Samui, Thailand.",
        "id": 1630116,
        "language": "en-US",
        "link": "https://www.foxnews.com/world/russian-tourist-dies-after-being-swept-away-massive-wave-while-doing-yoga-thailand",
        "manual_status_code": 0,
        "page_rating": 27,
        "page_rating_contents": 86,
        "page_rating_visits": 0,
        "page_rating_votes": 0,
        "permanent": false,
        "source__id": 120,
        "source_url": "https://moxie.foxnews.com/google-publisher/latest.xml",
        "status_code": 0,
        "tags": [],
        "thumbnail": "https://a57.foxnews.com/static.foxnews.com/foxnews.com/content/uploads/2024/12/931/523/kamilla-beliatskaya-collage.jpg?ve=1&tl=1",
        "title": "Russian tourist dies after being swept away by massive wave while doing yoga in Thailand",
        "vote": 0
    },
    {
        "age": null,
        "album": "",
        "author": null,
        "bookmarked": false,
        "comments": [],
        "date_published": "2024-12-02T17:23:58+00:00",
        "description": "Judge Kenneth Holder, a judge in New York, harangued Devin Spraggins during his sentencing on Monday.",
        "id": 1630117,
        "language": "en-US",
        "link": "https://www.foxnews.com/us/man-shot-rookie-nypd-cop-ripped-judge-didnt-give-damn-about-his-life",
        "manual_status_code": 0,
        "page_rating": 27,
        "page_rating_contents": 86,
        "page_rating_visits": 0,
        "page_rating_votes": 0,
        "permanent": false,
        "source__id": 120,
        "source_url": "https://moxie.foxnews.com/google-publisher/latest.xml",
        "status_code": 0,
        "tags": [],
        "thumbnail": "https://a57.foxnews.com/static.foxnews.com/foxnews.com/content/uploads/2024/12/931/523/copy-of-right-inset-58.png?ve=1&tl=1",
        "title": "Man who shot rookie NYPD cop ripped by judge: 'Didn't give a damn about his life'",
        "vote": 0
    },
    {
        "age": null,
        "album": "",
        "author": null,
        "bookmarked": false,
        "comments": [],
        "date_published": "2024-12-02T17:11:04+00:00",
        "description": "The Fox News Politics newsletter, with the latest updates on the Trump transition, exclusive interviews and more Fox News politics content.",
        "id": 1630118,
        "language": "en-US",
        "link": "https://www.foxnews.com/politics/fox-news-politics-pardon-us-karine",
        "manual_status_code": 0,
        "page_rating": 27,
        "page_rating_contents": 86,
        "page_rating_visits": 0,
        "page_rating_votes": 0,
        "permanent": false,
        "source__id": 120,
        "source_url": "https://moxie.foxnews.com/google-publisher/latest.xml",
        "status_code": 0,
        "tags": [],
        "thumbnail": "https://a57.foxnews.com/static.foxnews.com/foxnews.com/content/uploads/2024/12/931/523/trump-hunter-joe-biden.jpg?ve=1&tl=1",
        "title": "Fox News Politics: Pardon us, Karine",
        "vote": 0
    },
    {
        "age": null,
        "album": "",
        "author": null,
        "bookmarked": false,
        "comments": [],
        "date_published": "2024-12-02T17:08:57+00:00",
        "description": "Here are three Cyber Monday gift ideas that won&apos;t break the bank this Christmas. These enticing food baskets are all priced at under $25 and make thoughtful gifts.",
        "id": 1630119,
        "language": "en-US",
        "link": "https://www.foxnews.com/food-drink/cyber-monday-food-gift-baskets-under-25-season",
        "manual_status_code": 0,
        "page_rating": 27,
        "page_rating_contents": 86,
        "page_rating_visits": 0,
        "page_rating_votes": 0,
        "permanent": false,
        "source__id": 120,
        "source_url": "https://moxie.foxnews.com/google-publisher/latest.xml",
        "status_code": 0,
        "tags": [],
        "thumbnail": "https://a57.foxnews.com/static.foxnews.com/foxnews.com/content/uploads/2024/12/931/523/exchanging-christmas-gifts-over-food.jpg?ve=1&tl=1",
        "title": "These Cyber Monday food gift baskets are all under $25 this season",
        "vote": 0
    },
    {
        "age": null,
        "album": "",
        "author": null,
        "bookmarked": false,
        "comments": [],
        "date_published": "2024-12-02T17:00:37+00:00",
        "description": "Charlamagne argued that Democrats, after years of touting themselves as the party of democratic norms and ethical leadership, have utterly lost that claim in the public eye.",
        "id": 1629689,
        "language": "en-US",
        "link": "https://www.foxnews.com/media/charlamagne-calls-dems-give-up-charade-moral-high-ground-after-no-primary-pardoning-hunter",
        "manual_status_code": 0,
        "page_rating": 27,
        "page_rating_contents": 86,
        "page_rating_visits": 0,
        "page_rating_votes": 0,
        "permanent": false,
        "source__id": 120,
        "source_url": "https://moxie.foxnews.com/google-publisher/latest.xml",
        "status_code": 0,
        "tags": [],
        "thumbnail": "https://a57.foxnews.com/static.foxnews.com/foxnews.com/content/uploads/2024/12/931/523/charlamagne-radio-show.png?ve=1&tl=1",
        "title": "Charlamagne calls on Dems to give up charade of 'moral high ground' after no primary, pardoning Hunter",
        "vote": 0
    },
    {
        "age": null,
        "album": "",
        "author": null,
        "bookmarked": false,
        "comments": [],
        "date_published": "2024-12-02T17:00:34+00:00",
        "description": "The mayor of Frederick, Maryland, is under fire for announcing a planned legal defense appropriation to reportedly help illegal immigrants fight deportation",
        "id": 1629690,
        "language": "en-US",
        "link": "https://www.foxnews.com/politics/md-mayor-pushing-immigrant-legal-advocacy-fund-rebuff-trump-agenda",
        "manual_status_code": 0,
        "page_rating": 27,
        "page_rating_contents": 86,
        "page_rating_visits": 0,
        "page_rating_votes": 0,
        "permanent": false,
        "source__id": 120,
        "source_url": "https://moxie.foxnews.com/google-publisher/latest.xml",
        "status_code": 0,
        "tags": [],
        "thumbnail": "https://a57.foxnews.com/static.foxnews.com/foxnews.com/content/uploads/2024/12/1200/675/rederick-md-mayor-michael-oconnor.jpg?ve=1&tl=1",
        "title": "MD mayor under fire for pushing immigrant 'legal advocacy fund' to rebuff Trump-Homan agenda",
        "vote": 0
    },
    {
        "age": null,
        "album": "",
        "author": null,
        "bookmarked": false,
        "comments": [],
        "date_published": "2024-12-02T16:35:01+00:00",
        "description": "Carolina Panthers captain Sam Franklin Jr. needed to be restrained from running toward the Tampa Bay Buccaneers&apos; locker room as he threatened opposing linebacker Jose Ramirez.",
        "id": 1629691,
        "language": "en-US",
        "link": "https://www.foxnews.com/sports/panthers-sam-franklin-jr-restrained-from-running-bucs-locker-room-sends-threat-player-video",
        "manual_status_code": 0,
        "page_rating": 27,
        "page_rating_contents": 86,
        "page_rating_visits": 0,
        "page_rating_votes": 0,
        "permanent": false,
        "source__id": 120,
        "source_url": "https://moxie.foxnews.com/google-publisher/latest.xml",
        "status_code": 0,
        "tags": [],
        "thumbnail": "https://a57.foxnews.com/static.foxnews.com/foxnews.com/content/uploads/2024/12/931/523/sam-franklin-jr-1.jpg?ve=1&tl=1",
        "title": "Panthers' Sam Franklin Jr restrained from running to Bucs locker room, sends threat to player in video",
        "vote": 0
    },
    {
        "age": null,
        "album": "",
        "author": null,
        "bookmarked": false,
        "comments": [],
        "date_published": "2024-12-02T16:24:59+00:00",
        "description": "From water flossers to alarm clocks, here are five holiday gift ideas focused on health and wellness that are discounted on Amazon this Cyber Monday.",
        "id": 1629692,
        "language": "en-US",
        "link": "https://www.foxnews.com/health/cyber-monday-deals-health-wellness-gifts-check-out-hot-products-sale",
        "manual_status_code": 0,
        "page_rating": 27,
        "page_rating_contents": 86,
        "page_rating_visits": 0,
        "page_rating_votes": 0,
        "permanent": false,
        "source__id": 120,
        "source_url": "https://moxie.foxnews.com/google-publisher/latest.xml",
        "status_code": 0,
        "tags": [],
        "thumbnail": "https://a57.foxnews.com/static.foxnews.com/foxnews.com/content/uploads/2024/12/931/523/istock-2164616053.png?ve=1&tl=1",
        "title": "Cyber Monday deals on health and wellness gifts: Check out these hot products on sale",
        "vote": 0
    },
    {
        "age": null,
        "album": "",
        "author": null,
        "bookmarked": false,
        "comments": [],
        "date_published": "2024-12-02T15:50:11+00:00",
        "description": "After President Joe Biden issued a unilateral pardon for his son, Hunter Biden, on Sunday, many are remembering the first son\u2019s cavalier attitude throughout his trials and convictions, indicating a presidential pardon could have been planned the entire time.",
        "id": 1629261,
        "language": "en-US",
        "link": "https://www.foxnews.com/politics/hunter-bidens-confident-demeanor-unearthed-video-raises-questions-dads-pardon-plans",
        "manual_status_code": 0,
        "page_rating": 27,
        "page_rating_contents": 86,
        "page_rating_visits": 0,
        "page_rating_votes": 0,
        "permanent": false,
        "source__id": 120,
        "source_url": "https://moxie.foxnews.com/google-publisher/latest.xml",
        "status_code": 0,
        "tags": [],
        "thumbnail": "https://a57.foxnews.com/static.foxnews.com/foxnews.com/content/uploads/2023/05/931/523/Joe-Biden-Hunter-Biden.jpg?ve=1&tl=1",
        "title": "Hunter Biden's confident demeanor in unearthed video raises questions about dad's pardon plans",
        "vote": 0
    },
    {
        "age": null,
        "album": "",
        "author": null,
        "bookmarked": false,
        "comments": [],
        "date_published": "2024-12-02T15:50:03+00:00",
        "description": "A traveler who said he was flying on Delta posted a video on Reddit showing that a passenger had a large dog in the row, sparking a discussion in the comments section.",
        "id": 1629262,
        "language": "en-US",
        "link": "https://www.foxnews.com/travel/airline-passenger-sparks-debate-being-seated-near-massive-dog-plane-couldnt-move",
        "manual_status_code": 0,
        "page_rating": 27,
        "page_rating_contents": 86,
        "page_rating_visits": 0,
        "page_rating_votes": 0,
        "permanent": false,
        "source__id": 120,
        "source_url": "https://moxie.foxnews.com/google-publisher/latest.xml",
        "status_code": 0,
        "tags": [],
        "thumbnail": "https://a57.foxnews.com/static.foxnews.com/foxnews.com/content/uploads/2024/12/931/523/gettyimages-3146526.jpg?ve=1&tl=1",
        "title": "Airline passenger sparks debate after being seated near massive dog on plane: 'Couldn't move'",
        "vote": 0
    },
    {
        "age": null,
        "album": "",
        "author": null,
        "bookmarked": false,
        "comments": [],
        "date_published": "2024-12-02T15:47:15+00:00",
        "description": "As Congress enters recess, the president&apos;s ability to appoint ambassadors and other positions in the government has a long history.",
        "id": 1629263,
        "language": "en-US",
        "link": "https://www.foxnews.com/politics/hitchhikers-guide-recess-appointments",
        "manual_status_code": 0,
        "page_rating": 27,
        "page_rating_contents": 86,
        "page_rating_visits": 0,
        "page_rating_votes": 0,
        "permanent": false,
        "source__id": 120,
        "source_url": "https://moxie.foxnews.com/google-publisher/latest.xml",
        "status_code": 0,
        "tags": [],
        "thumbnail": "https://a57.foxnews.com/static.foxnews.com/foxnews.com/content/uploads/2024/11/931/523/trump-2.jpg?ve=1&tl=1",
        "title": "Reporter's Notebook: The hitchhiker\u2019s guide to recess appointments",
        "vote": 0
    },
    {
        "age": null,
        "album": "",
        "author": null,
        "bookmarked": false,
        "comments": [],
        "date_published": "2024-12-02T15:45:13+00:00",
        "description": "&quot;Real Time&quot; host Bill Maher said he was thinking of quitting his political talk show because he didn&apos;t want to comment on Donald Trump anymore",
        "id": 1629264,
        "language": "en-US",
        "link": "https://www.foxnews.com/media/bill-maher-tells-jane-fonda-he-might-quit-show-because-trump-fatigue",
        "manual_status_code": 0,
        "page_rating": 27,
        "page_rating_contents": 86,
        "page_rating_visits": 0,
        "page_rating_votes": 0,
        "permanent": false,
        "source__id": 120,
        "source_url": "https://moxie.foxnews.com/google-publisher/latest.xml",
        "status_code": 0,
        "tags": [],
        "thumbnail": "https://a57.foxnews.com/static.foxnews.com/foxnews.com/content/uploads/2024/05/931/523/BillMaher53124.jpg?ve=1&tl=1",
        "title": "Bill Maher tells Jane Fonda he might 'quit' show because of Trump",
        "vote": 0
    },
    {
        "age": null,
        "album": "",
        "author": null,
        "bookmarked": false,
        "comments": [],
        "date_published": "2024-12-02T15:44:13+00:00",
        "description": "Find the tech gadget that will improve your day-to-day for a steal during Amazon&apos;s Cyber Monday event.",
        "id": 1629265,
        "language": "en-US",
        "link": "https://www.foxnews.com/lifestyle/amazon-cyber-monday-tech-gadgets",
        "manual_status_code": 0,
        "page_rating": 27,
        "page_rating_contents": 86,
        "page_rating_visits": 0,
        "page_rating_votes": 0,
        "permanent": false,
        "source__id": 120,
        "source_url": "https://moxie.foxnews.com/google-publisher/latest.xml",
        "status_code": 0,
        "tags": [],
        "thumbnail": "https://a57.foxnews.com/static.foxnews.com/foxnews.com/content/uploads/2024/11/931/524/commerce-cyber-monday-istock-1048397282.png?ve=1&tl=1",
        "title": "Amazon Cyber Monday: 15 tech gadgets you can get at a discount",
        "vote": 0
    },
    {
        "age": null,
        "album": "",
        "author": null,
        "bookmarked": false,
        "comments": [],
        "date_published": "2024-12-02T15:31:25+00:00",
        "description": "Old-fashioned check fraud is back in style, quintupling over the past year. Here are a few low-tech, practical means of protecting yourself.",
        "id": 1629266,
        "language": "en-US",
        "link": "https://www.foxnews.com/tech/crime-shot-up-400-how-protect-yourself",
        "manual_status_code": 0,
        "page_rating": 27,
        "page_rating_contents": 86,
        "page_rating_visits": 0,
        "page_rating_votes": 0,
        "permanent": false,
        "source__id": 120,
        "source_url": "https://moxie.foxnews.com/google-publisher/latest.xml",
        "status_code": 0,
        "tags": [],
        "thumbnail": "https://a57.foxnews.com/static.foxnews.com/foxnews.com/content/uploads/2023/04/931/523/1-WRITING-CHECK.jpg?ve=1&tl=1",
        "title": "This crime shot up 400% \u2014 how to protect yourself",
        "vote": 0
    },
    {
        "age": null,
        "album": "",
        "author": null,
        "bookmarked": false,
        "comments": [],
        "date_published": "2024-12-02T15:23:50+00:00",
        "description": "President-elect Trump took a hard stance Monday on the release of hostages being held captive by Hamas terrorists in Gaza for more than one year.",
        "id": 1629267,
        "language": "en-US",
        "link": "https://www.foxnews.com/politics/trump-promises-hell-to-pay-middle-east-hostages-not-released-takes-office",
        "manual_status_code": 0,
        "page_rating": 27,
        "page_rating_contents": 86,
        "page_rating_visits": 0,
        "page_rating_votes": 0,
        "permanent": false,
        "source__id": 120,
        "source_url": "https://moxie.foxnews.com/google-publisher/latest.xml",
        "status_code": 0,
        "tags": [],
        "thumbnail": "https://a57.foxnews.com/static.foxnews.com/foxnews.com/content/uploads/2024/11/931/523/trump-netanyahu.jpg?ve=1&tl=1",
        "title": "Trump promises 'hell to pay' in Middle East if hostages are not released before he takes office",
        "vote": 0
    },
    {
        "age": null,
        "album": "",
        "author": null,
        "bookmarked": false,
        "comments": [],
        "date_published": "2024-12-02T15:00:28+00:00",
        "description": "Tampa Bay Buccaneers quarterback Baker Mayfield shrugged off some of the controversy regarding the flag-planting incidents around college football.",
        "id": 1628826,
        "language": "en-US",
        "link": "https://www.foxnews.com/sports/bucs-baker-mayfield-sounds-off-college-football-flag-planting-drama-let-boys-play",
        "manual_status_code": 0,
        "page_rating": 27,
        "page_rating_contents": 86,
        "page_rating_visits": 0,
        "page_rating_votes": 0,
        "permanent": false,
        "source__id": 120,
        "source_url": "https://moxie.foxnews.com/google-publisher/latest.xml",
        "status_code": 0,
        "tags": [],
        "thumbnail": "https://a57.foxnews.com/static.foxnews.com/foxnews.com/content/uploads/2024/12/931/523/baker-mayfield.jpg?ve=1&tl=1",
        "title": "Bucs' Baker Mayfield sounds off on college football flag-planting drama: 'Let the boys play'",
        "vote": 0
    },
    {
        "age": null,
        "album": "",
        "author": null,
        "bookmarked": false,
        "comments": [],
        "date_published": "2024-12-02T14:53:01+00:00",
        "description": "The field of contenders bidding to steer the Democratic National Committee in the wake of the party&apos;s very disappointing results in last month&apos;s elections keeps growing.",
        "id": 1628827,
        "language": "en-US",
        "link": "https://www.foxnews.com/politics/democrats-disarray-more-candidates-jump-wide-open-race-dnc-chair",
        "manual_status_code": 0,
        "page_rating": 27,
        "page_rating_contents": 86,
        "page_rating_visits": 0,
        "page_rating_votes": 0,
        "permanent": false,
        "source__id": 120,
        "source_url": "https://moxie.foxnews.com/google-publisher/latest.xml",
        "status_code": 0,
        "tags": [],
        "thumbnail": "https://a57.foxnews.com/static.foxnews.com/foxnews.com/content/uploads/2023/02/931/523/Jaime-Harrison-DNC-chair-DNC-winter-meeting-Philadelphia-Feb.-4-2023.jpg?ve=1&tl=1",
        "title": "Democrats in Disarray: More candidates jump into wide-open race for DNC chair",
        "vote": 0
    },
    {
        "age": null,
        "album": "",
        "author": null,
        "bookmarked": false,
        "comments": [],
        "date_published": "2024-12-02T14:45:56+00:00",
        "description": "&quot;The View&quot; co-host Whoopi Goldberg scolded colleague Alyssa Farah Griffin on Monday for saying that President Biden lied to the public about pardoning his son.",
        "id": 1628828,
        "language": "en-US",
        "link": "https://www.foxnews.com/media/whoopi-goldberg-defends-biden-scolds-co-host-calling-him-liar-he-can-do-whatever-he-wants",
        "manual_status_code": 0,
        "page_rating": 27,
        "page_rating_contents": 86,
        "page_rating_visits": 0,
        "page_rating_votes": 0,
        "permanent": false,
        "source__id": 120,
        "source_url": "https://moxie.foxnews.com/google-publisher/latest.xml",
        "status_code": 0,
        "tags": [],
        "thumbnail": "https://a57.foxnews.com/static.foxnews.com/foxnews.com/content/uploads/2024/12/931/523/whoopi-goldberg-alyssa-hunter.jpg?ve=1&tl=1",
        "title": "Whoopi Goldberg defends Biden, scolds co-host for calling him a liar: 'He can do whatever he wants'",
        "vote": 0
    },
    {
        "age": null,
        "album": "",
        "author": null,
        "bookmarked": false,
        "comments": [],
        "date_published": "2024-12-02T14:43:09+00:00",
        "description": "In southern Lebanon, Israeli forces confront entrenched Hezbollah positions and question UNIFIL\u2019s ability to enforce its mandate even before the cease-fire agreement was drawn up.",
        "id": 1628829,
        "language": "en-US",
        "link": "https://www.foxnews.com/world/idf-soldiers-accuse-un-peacekeepers-enabling-hezbollah-terrorists-amid-increasing-cease-fire-violations",
        "manual_status_code": 0,
        "page_rating": 27,
        "page_rating_contents": 86,
        "page_rating_visits": 0,
        "page_rating_votes": 0,
        "permanent": false,
        "source__id": 120,
        "source_url": "https://moxie.foxnews.com/google-publisher/latest.xml",
        "status_code": 0,
        "tags": [],
        "thumbnail": "https://a57.foxnews.com/static.foxnews.com/foxnews.com/content/uploads/2024/06/931/523/GettyImages-2044589811.jpg?ve=1&tl=1",
        "title": "IDF soldiers accuse UN peacekeepers of enabling Hezbollah terrorists amid increasing cease-fire violations",
        "vote": 0
    },
    {
        "age": null,
        "album": "",
        "author": null,
        "bookmarked": false,
        "comments": [],
        "date_published": "2024-12-02T14:35:25+00:00",
        "description": "Spend less than $100 on popular Walmart items like Beats headphones, Ninja kitchen appliances, LEGOS and Skechers.",
        "id": 1628830,
        "language": "en-US",
        "link": "https://www.foxnews.com/lifestyle/walmart-cyber-monday-sale",
        "manual_status_code": 0,
        "page_rating": 27,
        "page_rating_contents": 86,
        "page_rating_visits": 0,
        "page_rating_votes": 0,
        "permanent": false,
        "source__id": 120,
        "source_url": "https://moxie.foxnews.com/google-publisher/latest.xml",
        "status_code": 0,
        "tags": [],
        "thumbnail": "https://a57.foxnews.com/static.foxnews.com/foxnews.com/content/uploads/2024/12/931/524/istock-2127098695.jpg?ve=1&tl=1",
        "title": "Walmart\u2019s Cyber Monday sale: 15 deals under $100",
        "vote": 0
    },
    {
        "age": null,
        "album": "",
        "author": null,
        "bookmarked": false,
        "comments": [],
        "date_published": "2024-12-02T14:16:40+00:00",
        "description": "First lady Jill Biden said she supports the pardon for her son, Hunter Biden, when asked about it during a holiday event at the White House on Monday.",
        "id": 1628831,
        "language": "en-US",
        "link": "https://www.foxnews.com/politics/of-course-i-support-pardon-my-son-jill-biden-tells-reporter",
        "manual_status_code": 0,
        "page_rating": 27,
        "page_rating_contents": 86,
        "page_rating_visits": 0,
        "page_rating_votes": 0,
        "permanent": false,
        "source__id": 120,
        "source_url": "https://moxie.foxnews.com/google-publisher/latest.xml",
        "status_code": 0,
        "tags": [],
        "thumbnail": "https://a57.foxnews.com/static.foxnews.com/foxnews.com/content/uploads/2024/06/931/523/Hunter-Biden-Delaware-Trial-Day-7-Verdict_34.jpg?ve=1&tl=1",
        "title": "'Of course I support the pardon of my son,' Jill Biden tells reporter",
        "vote": 0
    },
    {
        "age": null,
        "album": "",
        "author": null,
        "bookmarked": false,
        "comments": [],
        "date_published": "2024-12-02T14:16:23+00:00",
        "description": "If you missed these top rated books among readers in 2024, including &quot;Bride,&quot; &quot;House of Flame and Shadow&quot; and &quot;Just for the Summer,&quot; you can catch up in 2025.",
        "id": 1628832,
        "language": "en-US",
        "link": "https://www.foxnews.com/lifestyle/top-rated-books-of-the-year",
        "manual_status_code": 0,
        "page_rating": 27,
        "page_rating_contents": 86,
        "page_rating_visits": 0,
        "page_rating_votes": 0,
        "permanent": false,
        "source__id": 120,
        "source_url": "https://moxie.foxnews.com/google-publisher/latest.xml",
        "status_code": 0,
        "tags": [],
        "thumbnail": "https://a57.foxnews.com/static.foxnews.com/foxnews.com/content/uploads/2024/12/931/523/sarah-j-maas-author.jpg?ve=1&tl=1",
        "title": "8 top-rated books of 2024 that you can catch up on in 2025: Sarah J Maas, Freida McFadden among the authors",
        "vote": 0
    },
    {
        "age": null,
        "album": "",
        "author": null,
        "bookmarked": false,
        "comments": [],
        "date_published": "2024-12-02T14:10:56+00:00",
        "description": "The Congressional Select Subcommittee on the Coronavirus Pandemic released its final 520-page report on Monday, revealing details the origin of the virus.",
        "id": 1628833,
        "language": "en-US",
        "link": "https://www.foxnews.com/politics/covid-most-likely-leaked-from-wuhan-lab-social-distancing-not-based-science-select-committee-finds",
        "manual_status_code": 0,
        "page_rating": 27,
        "page_rating_contents": 86,
        "page_rating_visits": 0,
        "page_rating_votes": 0,
        "permanent": false,
        "source__id": 120,
        "source_url": "https://moxie.foxnews.com/google-publisher/latest.xml",
        "status_code": 0,
        "tags": [],
        "thumbnail": "https://a57.foxnews.com/static.foxnews.com/foxnews.com/content/uploads/2023/06/931/523/wuhan-lab.jpg?ve=1&tl=1",
        "title": "COVID 'most likely' leaked from Wuhan lab, social distancing 'not based on science,' select committee finds",
        "vote": 0
    },
    {
        "age": null,
        "album": "",
        "author": null,
        "bookmarked": false,
        "comments": [],
        "date_published": "2024-12-02T14:09:21+00:00",
        "description": "Margot Robbie thought she ruined her career after she went off script while auditioning for &quot;The Wolf of Wall Street.&quot; The actress slapped Leonardo DiCaprio instead of kissing him.",
        "id": 1628834,
        "language": "en-US",
        "link": "https://www.foxnews.com/entertainment/margot-robbie-worried-leonardo-dicaprio-slap-would-get-her-arrested-during-wolf-wall-street-audition",
        "manual_status_code": 0,
        "page_rating": 27,
        "page_rating_contents": 86,
        "page_rating_visits": 0,
        "page_rating_votes": 0,
        "permanent": false,
        "source__id": 120,
        "source_url": "https://moxie.foxnews.com/google-publisher/latest.xml",
        "status_code": 0,
        "tags": [],
        "thumbnail": "https://a57.foxnews.com/static.foxnews.com/foxnews.com/content/uploads/2024/12/931/523/margot_robbie_wolf_of_wall_street.jpg?ve=1&tl=1",
        "title": "Margot Robbie worried Leonardo DiCaprio slap would get her arrested during 'Wolf of Wall Street' audition",
        "vote": 0
    },
    {
        "age": null,
        "album": "",
        "author": null,
        "bookmarked": false,
        "comments": [],
        "date_published": "2024-12-02T14:00:06+00:00",
        "description": "The Biden administration is announcing a $725 million weapons package for Ukraine less than two months before President-elect Donald Trump takes office, a U.S. official says.",
        "id": 1628835,
        "language": "en-US",
        "link": "https://www.foxnews.com/world/biden-administration-announce-725m-weapons-package-ukraine-months-before-trump-sworn",
        "manual_status_code": 0,
        "page_rating": 27,
        "page_rating_contents": 86,
        "page_rating_visits": 0,
        "page_rating_votes": 0,
        "permanent": false,
        "source__id": 120,
        "source_url": "https://moxie.foxnews.com/google-publisher/latest.xml",
        "status_code": 0,
        "tags": [],
        "thumbnail": "https://a57.foxnews.com/static.foxnews.com/foxnews.com/content/uploads/2024/12/931/523/zelenskyy-biden.jpg?ve=1&tl=1",
        "title": "Biden administration to announce $725M weapons package to Ukraine months before Trump is sworn in",
        "vote": 0
    },
    {
        "age": null,
        "album": "",
        "author": null,
        "bookmarked": false,
        "comments": [],
        "date_published": "2024-12-02T13:56:10+00:00",
        "description": "The Biden administration is blocking mining in a key region that produces nearly half of the nation&apos;s coal over alleged &quot;climate change&quot; concerns.",
        "id": 1627511,
        "language": "en-US",
        "link": "https://www.foxnews.com/politics/biden-blocks-new-mining-region-produces-40-nations-coal-disaster",
        "manual_status_code": 0,
        "page_rating": 27,
        "page_rating_contents": 86,
        "page_rating_visits": 0,
        "page_rating_votes": 0,
        "permanent": false,
        "source__id": 120,
        "source_url": "https://moxie.foxnews.com/google-publisher/latest.xml",
        "status_code": 0,
        "tags": [],
        "thumbnail": "https://a57.foxnews.com/static.foxnews.com/foxnews.com/content/uploads/2024/12/931/523/biden-prb.jpg?ve=1&tl=1",
        "title": "Biden blocks new mining in region that produces about 40% of nation's coal: 'It's a disaster'",
        "vote": 0
    },
    {
        "age": null,
        "album": "",
        "author": null,
        "bookmarked": false,
        "comments": [],
        "date_published": "2024-12-02T13:46:32+00:00",
        "description": "San Francisco 49ers All-Pro offensive lineman Trent Williams and his wife, Sondra, mourned the loss of their newborn child. Sondra posted a video about their loss.",
        "id": 1627512,
        "language": "en-US",
        "link": "https://www.foxnews.com/sports/49ers-all-pro-trent-williams-wife-sondra-mourn-death-newborn-son",
        "manual_status_code": 0,
        "page_rating": 27,
        "page_rating_contents": 86,
        "page_rating_visits": 0,
        "page_rating_votes": 0,
        "permanent": false,
        "source__id": 120,
        "source_url": "https://moxie.foxnews.com/google-publisher/latest.xml",
        "status_code": 0,
        "tags": [],
        "thumbnail": "https://a57.foxnews.com/static.foxnews.com/foxnews.com/content/uploads/2024/12/931/523/trent-williams-wife.jpg?ve=1&tl=1",
        "title": "49ers All-Pro Trent Williams, wife Sondra mourn death of newborn son",
        "vote": 0
    },
    {
        "age": null,
        "album": "",
        "author": null,
        "bookmarked": false,
        "comments": [],
        "date_published": "2024-12-02T13:46:01+00:00",
        "description": "House Republicans could begin next year with just a one-seat majority after losses in California and New York.",
        "id": 1627513,
        "language": "en-US",
        "link": "https://www.foxnews.com/politics/single-house-race-stands-between-republicans-1-seat-majority",
        "manual_status_code": 0,
        "page_rating": 27,
        "page_rating_contents": 86,
        "page_rating_visits": 0,
        "page_rating_votes": 0,
        "permanent": false,
        "source__id": 120,
        "source_url": "https://moxie.foxnews.com/google-publisher/latest.xml",
        "status_code": 0,
        "tags": [],
        "thumbnail": "https://a57.foxnews.com/static.foxnews.com/foxnews.com/content/uploads/2024/04/931/523/johnson-jeffries-vacate.jpg?ve=1&tl=1",
        "title": "Single House race stands between Republicans and 1-seat majority",
        "vote": 0
    },
    {
        "age": null,
        "album": "",
        "author": null,
        "bookmarked": false,
        "comments": [],
        "date_published": "2024-12-02T13:39:23+00:00",
        "description": "The FBI has teamed up with Maine State Police in an effort to locate teenager Stefanie Damron, who was last seen in late September and has a history of running away.",
        "id": 1627514,
        "language": "en-US",
        "link": "https://www.foxnews.com/us/fbi-offers-15000-reward-maine-teenager-last-seen-more-than-2-months-ago",
        "manual_status_code": 0,
        "page_rating": 27,
        "page_rating_contents": 86,
        "page_rating_visits": 0,
        "page_rating_votes": 0,
        "permanent": false,
        "source__id": 120,
        "source_url": "https://moxie.foxnews.com/google-publisher/latest.xml",
        "status_code": 0,
        "tags": [],
        "thumbnail": "https://a57.foxnews.com/static.foxnews.com/foxnews.com/content/uploads/2024/12/931/523/maine-girl-missing.jpg?ve=1&tl=1",
        "title": "FBI offers $15K reward for Maine teenager last seen more than 2 months ago",
        "vote": 0
    },
    {
        "age": null,
        "album": "",
        "author": null,
        "bookmarked": false,
        "comments": [],
        "date_published": "2024-12-02T13:30:31+00:00",
        "description": "Liberal commentators defended President Biden for issuing a blanket pardon to his son Hunter after months of insisting he would not pardon him or commute his sentence.",
        "id": 1627515,
        "language": "en-US",
        "link": "https://www.foxnews.com/media/liberal-media-voices-defend-biden-hunter-pardon-mock-conservative-outrage",
        "manual_status_code": 0,
        "page_rating": 27,
        "page_rating_contents": 86,
        "page_rating_visits": 0,
        "page_rating_votes": 0,
        "permanent": false,
        "source__id": 120,
        "source_url": "https://moxie.foxnews.com/google-publisher/latest.xml",
        "status_code": 0,
        "tags": [],
        "thumbnail": "https://a57.foxnews.com/static.foxnews.com/foxnews.com/content/uploads/2024/12/931/523/biden-hunter-biden.jpg?ve=1&tl=1",
        "title": "Liberal media voices defend Biden for Hunter pardon, mock conservative outrage",
        "vote": 0
    },
    {
        "age": null,
        "album": "",
        "author": null,
        "bookmarked": false,
        "comments": [],
        "date_published": "2024-12-02T13:25:19+00:00",
        "description": "Elton John says he no longer has his eyesight following a severe infection, which he revealed in September, first losing vision in his right eye.",
        "id": 1627516,
        "language": "en-US",
        "link": "https://www.foxnews.com/entertainment/elton-john-has-lost-my-eyesight-following-severe-infection",
        "manual_status_code": 0,
        "page_rating": 27,
        "page_rating_contents": 86,
        "page_rating_visits": 0,
        "page_rating_votes": 0,
        "permanent": false,
        "source__id": 120,
        "source_url": "https://moxie.foxnews.com/google-publisher/latest.xml",
        "status_code": 0,
        "tags": [],
        "thumbnail": "https://a57.foxnews.com/static.foxnews.com/foxnews.com/content/uploads/2024/12/931/523/eltonjohn.jpg?ve=1&tl=1",
        "title": "Elton John has \u2018lost my eyesight\u2019 following severe infection",
        "vote": 0
    },
    {
        "age": null,
        "album": "",
        "author": null,
        "bookmarked": false,
        "comments": [],
        "date_published": "2024-12-02T13:23:36+00:00",
        "description": "Bronx Congressman Ritchie Torres has a message for antisemites getting paid off taxpayers&apos; dime \u2013 and it&apos;s something President-elect Trump has said before.",
        "id": 1627517,
        "language": "en-US",
        "link": "https://www.foxnews.com/us/nyc-dem-slams-mayor-quotes-trump-fiery-post-against-antisemitic-waste-taxpayer-money-youre-fired",
        "manual_status_code": 0,
        "page_rating": 27,
        "page_rating_contents": 86,
        "page_rating_visits": 0,
        "page_rating_votes": 0,
        "permanent": false,
        "source__id": 120,
        "source_url": "https://moxie.foxnews.com/google-publisher/latest.xml",
        "status_code": 0,
        "tags": [],
        "thumbnail": "https://a57.foxnews.com/static.foxnews.com/foxnews.com/content/uploads/2024/11/931/523/gettyimages-1237824852-scaled-e1732544330300.jpg?ve=1&tl=1",
        "title": "NYC Dem slams mayor, quotes Trump in fiery post against antisemitic waste of taxpayer money: 'You're fired'",
        "vote": 0
    },
    {
        "age": null,
        "album": "",
        "author": null,
        "bookmarked": false,
        "comments": [],
        "date_published": "2024-12-02T13:16:34+00:00",
        "description": "The White House defended President Biden&apos;s May social media post that &quot;no one is above the law&quot; following Biden pardoning his son, Hunter Biden.",
        "id": 1627518,
        "language": "en-US",
        "link": "https://www.foxnews.com/politics/biden-still-believes-no-one-above-law-white-house-says-wake-hunter-pardon",
        "manual_status_code": 0,
        "page_rating": 27,
        "page_rating_contents": 86,
        "page_rating_visits": 0,
        "page_rating_votes": 0,
        "permanent": false,
        "source__id": 120,
        "source_url": "https://moxie.foxnews.com/google-publisher/latest.xml",
        "status_code": 0,
        "tags": [],
        "thumbnail": "https://a57.foxnews.com/static.foxnews.com/foxnews.com/content/uploads/2024/11/931/523/biden.jpg?ve=1&tl=1",
        "title": "Biden still believes 'no one is above the law,' White House says in wake of Hunter pardon",
        "vote": 0
    },
    {
        "age": null,
        "album": "",
        "author": null,
        "bookmarked": false,
        "comments": [],
        "date_published": "2024-12-02T13:10:38+00:00",
        "description": "This Cyber Monday, upgrade your vacuum&apos;s suction power and ditch the cord with a good deal.",
        "id": 1627519,
        "language": "en-US",
        "link": "https://www.foxnews.com/lifestyle/cyber-monday-vacuum-cleaner-deals",
        "manual_status_code": 0,
        "page_rating": 27,
        "page_rating_contents": 86,
        "page_rating_visits": 0,
        "page_rating_votes": 0,
        "permanent": false,
        "source__id": 120,
        "source_url": "https://moxie.foxnews.com/google-publisher/latest.xml",
        "status_code": 0,
        "tags": [],
        "thumbnail": "https://a57.foxnews.com/static.foxnews.com/foxnews.com/content/uploads/2024/11/931/524/commerce-vaccum-cleaners-istock-1393641373.png?ve=1&tl=1",
        "title": "Cyber Monday: 6 cordless vacuum deals you can't miss",
        "vote": 0
    },
    {
        "age": null,
        "album": "",
        "author": null,
        "bookmarked": false,
        "comments": [],
        "date_published": "2024-12-02T13:05:15+00:00",
        "description": "Make the most of Cyber Monday with this holiday gift guide focused on the traveler in your life. From lightweight carry-ons to warm wraps, tech and more, consider these options.",
        "id": 1627520,
        "language": "en-US",
        "link": "https://www.foxnews.com/travel/cyber-monday-deals-travel-gifts-see-practical-picks",
        "manual_status_code": 0,
        "page_rating": 27,
        "page_rating_contents": 86,
        "page_rating_visits": 0,
        "page_rating_votes": 0,
        "permanent": false,
        "source__id": 120,
        "source_url": "https://moxie.foxnews.com/google-publisher/latest.xml",
        "status_code": 0,
        "tags": [],
        "thumbnail": "https://a57.foxnews.com/static.foxnews.com/foxnews.com/content/uploads/2024/12/931/523/istock-1448597991.jpg?ve=1&tl=1",
        "title": "Cyber Monday deals on travel gifts: See these practical picks",
        "vote": 0
    },
    {
        "age": null,
        "album": "",
        "author": null,
        "bookmarked": false,
        "comments": [],
        "date_published": "2024-12-02T13:03:55+00:00",
        "description": "Dozens are hospitalized after massive protests broke out across Georgia following the pro-Putin government&apos;s move halting decadeslong talks on joining the EU amid increasing ties with Russia.",
        "id": 1627521,
        "language": "en-US",
        "link": "https://www.foxnews.com/world/pro-putin-leader-backs-harsh-crackdown-over-40-people-hospitalized-amid-protests-georgia",
        "manual_status_code": 0,
        "page_rating": 27,
        "page_rating_contents": 86,
        "page_rating_visits": 0,
        "page_rating_votes": 0,
        "permanent": false,
        "source__id": 120,
        "source_url": "https://moxie.foxnews.com/google-publisher/latest.xml",
        "status_code": 0,
        "tags": [],
        "thumbnail": "https://a57.foxnews.com/static.foxnews.com/foxnews.com/content/uploads/2024/12/931/523/geo-pro-3.jpg?ve=1&tl=1",
        "title": "Pro-Putin leader backs harsh crackdown as over 40 people hospitalized amid protests in Georgia",
        "vote": 0
    },
    {
        "age": null,
        "album": "",
        "author": null,
        "bookmarked": false,
        "comments": [],
        "date_published": "2024-12-02T13:00:29+00:00",
        "description": "MSNBC had lowest-rated, non-holiday weekday among the advertiser-coveted demographic of adults age 25-54 in 20 years last Tuesday as the liberal network continues to struggle.",
        "id": 1627522,
        "language": "en-US",
        "link": "https://www.foxnews.com/media/msnbc-posts-another-critical-ratings-low-among-critical-demo",
        "manual_status_code": 0,
        "page_rating": 27,
        "page_rating_contents": 86,
        "page_rating_visits": 0,
        "page_rating_votes": 0,
        "permanent": false,
        "source__id": 120,
        "source_url": "https://moxie.foxnews.com/google-publisher/latest.xml",
        "status_code": 0,
        "tags": [],
        "thumbnail": "https://a57.foxnews.com/static.foxnews.com/foxnews.com/content/uploads/2024/11/931/523/msnbc-hosts-.png?ve=1&tl=1",
        "title": "MSNBC posts another critical ratings low among critical demo",
        "vote": 0
    },
    {
        "age": null,
        "album": "",
        "author": null,
        "bookmarked": false,
        "comments": [],
        "date_published": "2024-12-02T12:59:46+00:00",
        "description": "Pittsburgh Steelers running back Najee Harris said Sunday a Thanksgiving meal was to blame for his brief absence in the win over Cincinnati Bengals.",
        "id": 1627523,
        "language": "en-US",
        "link": "https://www.foxnews.com/sports/steelers-najee-harris-blames-brief-absence-teammates-girlfriends-thanksgiving-meal",
        "manual_status_code": 0,
        "page_rating": 27,
        "page_rating_contents": 86,
        "page_rating_visits": 0,
        "page_rating_votes": 0,
        "permanent": false,
        "source__id": 120,
        "source_url": "https://moxie.foxnews.com/google-publisher/latest.xml",
        "status_code": 0,
        "tags": [],
        "thumbnail": "https://a57.foxnews.com/static.foxnews.com/foxnews.com/content/uploads/2024/12/931/523/najee-harris2.jpg?ve=1&tl=1",
        "title": "Steelers' Najee Harris blames brief absence on teammate's girlfriend's Thanksgiving meal",
        "vote": 0
    },
    {
        "age": null,
        "album": "",
        "author": null,
        "bookmarked": false,
        "comments": [],
        "date_published": "2024-12-02T12:45:43+00:00",
        "description": "Tom Homan said Monday that he plans to meet with New York City Mayor Eric Adams in the upcoming days and is willing to &quot;work together&quot; with anyone.",
        "id": 1627524,
        "language": "en-US",
        "link": "https://www.foxnews.com/media/trump-border-czar-tom-homan-meet-nyc-mayor-eric-adams-address-migrant-crisis-lets-get-done",
        "manual_status_code": 0,
        "page_rating": 27,
        "page_rating_contents": 86,
        "page_rating_visits": 0,
        "page_rating_votes": 0,
        "permanent": false,
        "source__id": 120,
        "source_url": "https://moxie.foxnews.com/google-publisher/latest.xml",
        "status_code": 0,
        "tags": [],
        "thumbnail": "https://a57.foxnews.com/static.foxnews.com/foxnews.com/content/uploads/2024/12/931/523/homan_adams.jpg?ve=1&tl=1",
        "title": "Trump border czar Homan says he'll meet with NYC Mayor Adams to address migrant crisis: Let's 'get this done'",
        "vote": 0
    },
    {
        "age": null,
        "album": "",
        "author": null,
        "bookmarked": false,
        "comments": [],
        "date_published": "2024-12-02T12:33:41+00:00",
        "description": "U.S. Capitol Police arrested a staff member of House Democrat Joe Morelle of New York after he allegedly was found with ammunition inside a bag he was carrying.",
        "id": 1627525,
        "language": "en-US",
        "link": "https://www.foxnews.com/politics/us-capitol-police-arrest-house-democrat-staff-member-finding-ammunition-bag",
        "manual_status_code": 0,
        "page_rating": 27,
        "page_rating_contents": 86,
        "page_rating_visits": 0,
        "page_rating_votes": 0,
        "permanent": false,
        "source__id": 120,
        "source_url": "https://moxie.foxnews.com/google-publisher/latest.xml",
        "status_code": 0,
        "tags": [],
        "thumbnail": "https://a57.foxnews.com/static.foxnews.com/foxnews.com/content/uploads/2024/12/931/523/michael-hopkins.jpg?ve=1&tl=1",
        "title": "US Capitol Police arrest House Democrat staff member after finding ammunition",
        "vote": 0
    },
    {
        "age": null,
        "album": "",
        "author": null,
        "bookmarked": false,
        "comments": [],
        "date_published": "2024-12-02T12:30:39+00:00",
        "description": "San Francisco 49ers star Christian McCaffrey could &quot;potentially&quot; be lost for the season with a knee injury, head coach Kyle Shanahan said Sunday night.",
        "id": 1627526,
        "language": "en-US",
        "link": "https://www.foxnews.com/sports/49ers-christian-mccaffrey-suffered-potentially-season-ending-knee-injury-vs-bills-coach-says",
        "manual_status_code": 0,
        "page_rating": 27,
        "page_rating_contents": 86,
        "page_rating_visits": 0,
        "page_rating_votes": 0,
        "permanent": false,
        "source__id": 120,
        "source_url": "https://moxie.foxnews.com/google-publisher/latest.xml",
        "status_code": 0,
        "tags": [],
        "thumbnail": "https://a57.foxnews.com/static.foxnews.com/foxnews.com/content/uploads/2024/12/931/523/christian-mccaffrey2.jpg?ve=1&tl=1",
        "title": "49ers' Christian McCaffrey suffered 'potentially' season-ending knee injury vs Bills, coach says",
        "vote": 0
    },
    {
        "age": null,
        "album": "",
        "author": null,
        "bookmarked": false,
        "comments": [],
        "date_published": "2024-12-02T12:27:00+00:00",
        "description": "The Harris campaign is coming under fire for continuing to request donations from supporters weeks after former President Trump was elected to a second term.",
        "id": 1627527,
        "language": "en-US",
        "link": "https://www.foxnews.com/politics/harris-campaign-still-asking-donations-weeks-after-massive-loss-trump",
        "manual_status_code": 0,
        "page_rating": 27,
        "page_rating_contents": 86,
        "page_rating_visits": 0,
        "page_rating_votes": 0,
        "permanent": false,
        "source__id": 120,
        "source_url": "https://moxie.foxnews.com/google-publisher/latest.xml",
        "status_code": 0,
        "tags": [],
        "thumbnail": "https://a57.foxnews.com/static.foxnews.com/foxnews.com/content/uploads/2022/06/931/523/Kamala-Harris-Texas-Migrant-Deaths.jpg?ve=1&tl=1",
        "title": "Harris campaign still asking for donations weeks after massive loss to Trump",
        "vote": 0
    },
    {
        "age": null,
        "album": "",
        "author": null,
        "bookmarked": false,
        "comments": [],
        "date_published": "2024-12-02T12:25:50+00:00",
        "description": "San Jose State volleyball&apos;s Brooke Slusser gave Fox News Digital the inside story of her team&apos;s Thanksgiving week trip to Las Vegas amid a national controversy.",
        "id": 1627528,
        "language": "en-US",
        "link": "https://www.foxnews.com/sports/sjsu-trans-player-traumatized-teammate-had-sin-city-thanksgiving-last-trip-together-lawsuits-rage",
        "manual_status_code": 0,
        "page_rating": 27,
        "page_rating_contents": 86,
        "page_rating_visits": 0,
        "page_rating_votes": 0,
        "permanent": false,
        "source__id": 120,
        "source_url": "https://moxie.foxnews.com/google-publisher/latest.xml",
        "status_code": 0,
        "tags": [],
        "thumbnail": "https://a57.foxnews.com/static.foxnews.com/foxnews.com/content/uploads/2024/12/931/523/blaire-fleming-brooke-slusser-copy.jpg?ve=1&tl=1",
        "title": "SJSU trans player and traumatized teammate had Sin City Thanksgiving in last trip together as lawsuits rage on",
        "vote": 0
    },
    {
        "age": null,
        "album": "",
        "author": null,
        "bookmarked": false,
        "comments": [],
        "date_published": "2024-12-02T11:56:44+00:00",
        "description": "A Colorado dentist accused of killing his wife by poisoning her protein shakes now faces a new charge for allegedly attempting to get a fellow inmate to murder a detective.",
        "id": 1627529,
        "language": "en-US",
        "link": "https://www.foxnews.com/us/dentist-charged-killing-wife-poisoning-her-shakes-now-accused-trying-have-detective-killed",
        "manual_status_code": 0,
        "page_rating": 27,
        "page_rating_contents": 86,
        "page_rating_visits": 0,
        "page_rating_votes": 0,
        "permanent": false,
        "source__id": 120,
        "source_url": "https://moxie.foxnews.com/google-publisher/latest.xml",
        "status_code": 0,
        "tags": [],
        "thumbnail": "https://a57.foxnews.com/static.foxnews.com/foxnews.com/content/uploads/2023/03/931/523/Angela-and-James-Craig.jpg?ve=1&tl=1",
        "title": "Dentist charged with killing wife by poisoning her shakes is now accused of trying to have detective killed",
        "vote": 0
    },
    {
        "age": null,
        "album": "",
        "author": null,
        "bookmarked": false,
        "comments": [],
        "date_published": "2024-12-02T11:44:33+00:00",
        "description": "Ellen DeGeneres&apos; UK farmhouse shared with wife Portia de Rossi did not flood, according to the former talk show host. DeGeneres shut down rumors in an Instagram post.",
        "id": 1627530,
        "language": "en-US",
        "link": "https://www.foxnews.com/entertainment/ellen-degeneres-shuts-down-rumors-her-uk-farmhouse-flooded-after-fleeing-us",
        "manual_status_code": 0,
        "page_rating": 27,
        "page_rating_contents": 86,
        "page_rating_visits": 0,
        "page_rating_votes": 0,
        "permanent": false,
        "source__id": 120,
        "source_url": "https://moxie.foxnews.com/google-publisher/latest.xml",
        "status_code": 0,
        "tags": [],
        "thumbnail": "https://static.foxnews.com/foxnews.com/content/uploads/2023/01/ellen-degeneres-portia-de-rossi.gif",
        "title": "Ellen DeGeneres shuts down rumors her UK farmhouse flooded after fleeing US",
        "vote": 0
    },
    {
        "age": null,
        "album": "",
        "author": null,
        "bookmarked": false,
        "comments": [],
        "date_published": "2024-12-02T11:43:31+00:00",
        "description": "Legal and political analysts are characterizing President Biden&apos;s stunning &quot;full and unconditional pardon&quot; of his son Hunter as an early holiday gift for President-elect Donald Trump.",
        "id": 1627531,
        "language": "en-US",
        "link": "https://www.foxnews.com/politics/president-bidens-pardon-son-hunter-political-gift-trump-going-forward",
        "manual_status_code": 0,
        "page_rating": 27,
        "page_rating_contents": 86,
        "page_rating_visits": 0,
        "page_rating_votes": 0,
        "permanent": false,
        "source__id": 120,
        "source_url": "https://moxie.foxnews.com/google-publisher/latest.xml",
        "status_code": 0,
        "tags": [],
        "thumbnail": "https://a57.foxnews.com/static.foxnews.com/foxnews.com/content/uploads/2024/05/931/523/Biden-Trump-split.png?ve=1&tl=1",
        "title": "President Biden's pardon of son Hunter a political gift for Trump going forward",
        "vote": 0
    },
    {
        "age": null,
        "album": "",
        "author": null,
        "bookmarked": false,
        "comments": [],
        "date_published": "2024-12-02T11:25:21+00:00",
        "description": "Reporters grilled White House press secretary Karine Jean-Pierre on Monday, after President Biden went back on his word and pardoned his son Hunter.",
        "id": 1627532,
        "language": "en-US",
        "link": "https://www.foxnews.com/politics/karine-jean-pierre-faces-press-grilling-after-biden-pardons-son-hunter",
        "manual_status_code": 0,
        "page_rating": 27,
        "page_rating_contents": 86,
        "page_rating_visits": 0,
        "page_rating_votes": 0,
        "permanent": false,
        "source__id": 120,
        "source_url": "https://moxie.foxnews.com/google-publisher/latest.xml",
        "status_code": 0,
        "tags": [],
        "thumbnail": "https://a57.foxnews.com/static.foxnews.com/foxnews.com/content/uploads/2023/11/931/523/Karine-Jean-Pierre.jpg?ve=1&tl=1",
        "title": "Karine Jean-Pierre faces press grilling after Biden pardons son Hunter",
        "vote": 0
    },
    {
        "age": null,
        "album": "",
        "author": null,
        "bookmarked": false,
        "comments": [],
        "date_published": "2024-12-02T11:15:04+00:00",
        "description": "In his pardon announcement on Sunday night, President Biden absurdly claimed that his son was \u201cselectively, and unfairly, prosecuted.&quot;\u00a0The opposite is true.",
        "id": 1627533,
        "language": "en-US",
        "link": "https://www.foxnews.com/opinion/gregg-jarrett-biden-lied-all-us-when-he-pardoned-hunter-he-put-himself-first",
        "manual_status_code": 0,
        "page_rating": 27,
        "page_rating_contents": 86,
        "page_rating_visits": 0,
        "page_rating_votes": 0,
        "permanent": false,
        "source__id": 120,
        "source_url": "https://moxie.foxnews.com/google-publisher/latest.xml",
        "status_code": 0,
        "tags": [],
        "thumbnail": "https://a57.foxnews.com/static.foxnews.com/foxnews.com/content/uploads/2024/12/931/523/hunter-biden.jpg?ve=1&tl=1",
        "title": "GREGG JARRETT: Biden lied to all of us when he pardoned Hunter. He put himself first",
        "vote": 0
    },
    {
        "age": null,
        "album": "",
        "author": null,
        "bookmarked": false,
        "comments": [],
        "date_published": "2024-12-02T09:12:43+00:00",
        "description": "The wife of Jacksonville Jaguars quarterback Trevor Lawrence, Marissa, spoke out about her husband following the brutal hit that forced his exit from Sunday&apos;s game.",
        "id": 1626716,
        "language": "en-US",
        "link": "https://www.foxnews.com/sports/marissa-lawrence-wife-jaguars-star-quarterback-thanks-fans-support-after-player-takes-brutal-hit",
        "manual_status_code": 0,
        "page_rating": 27,
        "page_rating_contents": 86,
        "page_rating_visits": 0,
        "page_rating_votes": 0,
        "permanent": false,
        "source__id": 120,
        "source_url": "https://moxie.foxnews.com/google-publisher/latest.xml",
        "status_code": 0,
        "tags": [],
        "thumbnail": "https://a57.foxnews.com/static.foxnews.com/foxnews.com/content/uploads/2024/12/931/523/marissa-lawrence2.jpg?ve=1&tl=1",
        "title": "Marissa Lawrence, wife of Jaguars star quarterback, thanks fans for support after player takes brutal hit",
        "vote": 0
    },
    {
        "age": null,
        "album": "",
        "author": null,
        "bookmarked": false,
        "comments": [],
        "date_published": "2024-12-02T09:02:42+00:00",
        "description": "In the 2020 election and throughout his term, President Biden repeatedly lied to the American public with an ease and impunity that shocked even many political veterans in Washington.",
        "id": 1626717,
        "language": "en-US",
        "link": "https://www.foxnews.com/opinion/jonathan-turley-joe-bidens-pardon-son-hunter-cements-his-legacy-liar-chief",
        "manual_status_code": 0,
        "page_rating": 27,
        "page_rating_contents": 86,
        "page_rating_visits": 0,
        "page_rating_votes": 0,
        "permanent": false,
        "source__id": 120,
        "source_url": "https://moxie.foxnews.com/google-publisher/latest.xml",
        "status_code": 0,
        "tags": [],
        "thumbnail": "https://a57.foxnews.com/static.foxnews.com/foxnews.com/content/uploads/2024/12/931/523/gettyimages-2187280340-scaled.jpg?ve=1&tl=1",
        "title": "JONATHAN TURLEY: Joe Biden's pardon of son Hunter cements his legacy as liar in chief",
        "vote": 0
    },
    {
        "age": null,
        "album": "",
        "author": null,
        "bookmarked": false,
        "comments": [],
        "date_published": "2024-12-02T09:00:14+00:00",
        "description": "Gov. Gavin Newsom is preparing his Democrat-majority state legislature to establish a hefty litigation fund ahead of President-elect Donald Trump&apos;s second administration.",
        "id": 1626718,
        "language": "en-US",
        "link": "https://www.foxnews.com/politics/newsom-proposes-25m-from-state-legislature-trump-proof-california",
        "manual_status_code": 0,
        "page_rating": 27,
        "page_rating_contents": 86,
        "page_rating_visits": 0,
        "page_rating_votes": 0,
        "permanent": false,
        "source__id": 120,
        "source_url": "https://moxie.foxnews.com/google-publisher/latest.xml",
        "status_code": 0,
        "tags": [],
        "thumbnail": "https://a57.foxnews.com/static.foxnews.com/foxnews.com/content/uploads/2024/11/931/523/newsom-trump-split.jpg?ve=1&tl=1",
        "title": "Newsom proposes $25M from state legislature to 'Trump-proof' California",
        "vote": 0
    },
    {
        "age": null,
        "album": "",
        "author": null,
        "bookmarked": false,
        "comments": [],
        "date_published": "2024-12-02T08:54:02+00:00",
        "description": "Amazon offers great deals on electronics and small appliances during its Cyber Monday event, which runs through Dec. 2 at 11:59 PST.",
        "id": 1626719,
        "language": "en-US",
        "link": "https://www.foxnews.com/lifestyle/amazon-cyber-monday-electronics-gadgets-deals",
        "manual_status_code": 0,
        "page_rating": 27,
        "page_rating_contents": 86,
        "page_rating_visits": 0,
        "page_rating_votes": 0,
        "permanent": false,
        "source__id": 120,
        "source_url": "https://moxie.foxnews.com/google-publisher/latest.xml",
        "status_code": 0,
        "tags": [],
        "thumbnail": "https://a57.foxnews.com/static.foxnews.com/foxnews.com/content/uploads/2024/11/931/524/commerce-cyber-monday-sales-istock-1346571203-1.png?ve=1&tl=1",
        "title": "Amazon Cyber Monday: Grab discounts on Amazon brand electronics and more",
        "vote": 0
    },
    {
        "age": null,
        "album": "",
        "author": null,
        "bookmarked": false,
        "comments": [],
        "date_published": "2024-12-02T08:53:37+00:00",
        "description": "Molly Jong Fast, a MSNBC contributor, was left speechless by the news that President Biden pardoned his son, Hunter Biden, saying she needed some time to process it.",
        "id": 1626720,
        "language": "en-US",
        "link": "https://www.foxnews.com/media/liberal-msnbc-contributor-speechless-over-hunter-biden-pardon-have-process-sorry",
        "manual_status_code": 0,
        "page_rating": 27,
        "page_rating_contents": 86,
        "page_rating_visits": 0,
        "page_rating_votes": 0,
        "permanent": false,
        "source__id": 120,
        "source_url": "https://moxie.foxnews.com/google-publisher/latest.xml",
        "status_code": 0,
        "tags": [],
        "thumbnail": "https://a57.foxnews.com/static.foxnews.com/foxnews.com/content/uploads/2024/12/931/523/molly-jong-fast-hunter.jpg?ve=1&tl=1",
        "title": "Liberal MSNBC contributor speechless over Hunter Biden pardon: 'I have to process it ... I'm sorry'",
        "vote": 0
    },
    {
        "age": null,
        "album": "",
        "author": null,
        "bookmarked": false,
        "comments": [],
        "date_published": "2024-12-02T08:14:58+00:00",
        "description": "Pittsburgh Steelers head coach Mike Tomlin called out wide receiver George Pickens on Sunday following the team&apos;s close win over the Cincinnati Bengals.",
        "id": 1626254,
        "language": "en-US",
        "link": "https://www.foxnews.com/sports/steelers-mike-tomlin-calls-out-george-pickens-hes-got-grow-up-hurry",
        "manual_status_code": 0,
        "page_rating": 27,
        "page_rating_contents": 86,
        "page_rating_visits": 0,
        "page_rating_votes": 0,
        "permanent": false,
        "source__id": 120,
        "source_url": "https://moxie.foxnews.com/google-publisher/latest.xml",
        "status_code": 0,
        "tags": [],
        "thumbnail": "https://a57.foxnews.com/static.foxnews.com/foxnews.com/content/uploads/2024/12/931/523/george-pickens2.jpg?ve=1&tl=1",
        "title": "Steelers' Mike Tomlin calls out George Pickens: 'He's got to grow up in a hurry'",
        "vote": 0
    },
    {
        "age": null,
        "album": "",
        "author": null,
        "bookmarked": false,
        "comments": [],
        "date_published": "2024-12-02T08:13:46+00:00",
        "description": "President Biden had repeatedly stated he would not grant clemency to his son Hunter Biden before ultimately pardoning him anyway on Sunday.",
        "id": 1626255,
        "language": "en-US",
        "link": "https://www.foxnews.com/politics/2-times-biden-said-he-would-not-pardon-son-hunter-biden",
        "manual_status_code": 0,
        "page_rating": 27,
        "page_rating_contents": 86,
        "page_rating_visits": 0,
        "page_rating_votes": 0,
        "permanent": false,
        "source__id": 120,
        "source_url": "https://moxie.foxnews.com/google-publisher/latest.xml",
        "status_code": 0,
        "tags": [],
        "thumbnail": "https://a57.foxnews.com/static.foxnews.com/foxnews.com/content/uploads/2024/12/931/523/gettyimages-2187280340-scaled.jpg?ve=1&tl=1",
        "title": "2 times Biden said he would not pardon son Hunter Biden",
        "vote": 0
    },
    {
        "age": null,
        "album": "",
        "author": null,
        "bookmarked": false,
        "comments": [],
        "date_published": "2024-12-02T08:05:10+00:00",
        "description": "New York City has a population of nearly 60,000 illegal migrants who have either been convicted of a crime or currently have criminal charges pending agains them.",
        "id": 1626256,
        "language": "en-US",
        "link": "https://www.foxnews.com/politics/nyc-home-nearly-60k-criminal-migrants-report",
        "manual_status_code": 0,
        "page_rating": 27,
        "page_rating_contents": 86,
        "page_rating_visits": 0,
        "page_rating_votes": 0,
        "permanent": false,
        "source__id": 120,
        "source_url": "https://moxie.foxnews.com/google-publisher/latest.xml",
        "status_code": 0,
        "tags": [],
        "thumbnail": "https://a57.foxnews.com/static.foxnews.com/foxnews.com/content/uploads/2024/12/931/523/gettyimages-1571943901.jpg?ve=1&tl=1",
        "title": "NYC home to nearly 60k \u2018criminal\u2019 migrants: Report",
        "vote": 0
    },
    {
        "age": null,
        "album": "",
        "author": null,
        "bookmarked": false,
        "comments": [],
        "date_published": "2024-12-02T08:00:13+00:00",
        "description": "James Van Der Beek shocked his &quot;The Real Full Monty&quot; castmates when he told them he had colorectal cancer, the disease the special is trying to raise awareness for.",
        "id": 1626257,
        "language": "en-US",
        "link": "https://www.foxnews.com/entertainment/james-van-der-beek-dropped-bomb-real-full-monty-co-stars-cancer",
        "manual_status_code": 0,
        "page_rating": 27,
        "page_rating_contents": 86,
        "page_rating_visits": 0,
        "page_rating_votes": 0,
        "permanent": false,
        "source__id": 120,
        "source_url": "https://moxie.foxnews.com/google-publisher/latest.xml",
        "status_code": 0,
        "tags": [],
        "thumbnail": "https://a57.foxnews.com/static.foxnews.com/foxnews.com/content/uploads/2024/11/931/523/jamesvanderbeekrealfullmonty.jpg?ve=1&tl=1",
        "title": "James Van Der Beek \u2018dropped a bomb\u2019 on \u2018Real Full Monty\u2019 co-stars with cancer",
        "vote": 0
    },
    {
        "age": null,
        "album": "",
        "author": null,
        "bookmarked": false,
        "comments": [],
        "date_published": "2024-12-02T07:57:55+00:00",
        "description": "Sen. Ted Cruz, R-Texas, in July predicted that President Biden would go back on his pledge to Americans and pardon his son Hunter.",
        "id": 1626258,
        "language": "en-US",
        "link": "https://www.foxnews.com/politics/ted-cruz-july-predicted-100-odds-biden-pardoning-son-hunter-after-election-day",
        "manual_status_code": 0,
        "page_rating": 27,
        "page_rating_contents": 86,
        "page_rating_visits": 0,
        "page_rating_votes": 0,
        "permanent": false,
        "source__id": 120,
        "source_url": "https://moxie.foxnews.com/google-publisher/latest.xml",
        "status_code": 0,
        "tags": [],
        "thumbnail": "https://a57.foxnews.com/static.foxnews.com/foxnews.com/content/uploads/2024/12/931/523/cruz-bidens-thumb.jpg?ve=1&tl=1",
        "title": "Ted Cruz in July predicted 100% odds of Biden pardoning son Hunter after Election Day",
        "vote": 0
    },
    {
        "age": null,
        "album": "",
        "author": null,
        "bookmarked": false,
        "comments": [],
        "date_published": "2024-12-02T07:45:25+00:00",
        "description": "A 21-year-old American-Israeli believed to have been held hostage since October 2023 was confirmed dead by the Israel Defense Forces on Monday.",
        "id": 1626259,
        "language": "en-US",
        "link": "https://www.foxnews.com/world/american-israeli-idf-platoon-commander-killed-battle-body-held-gaza-idf-says",
        "manual_status_code": 0,
        "page_rating": 27,
        "page_rating_contents": 86,
        "page_rating_visits": 0,
        "page_rating_votes": 0,
        "permanent": false,
        "source__id": 120,
        "source_url": "https://moxie.foxnews.com/google-publisher/latest.xml",
        "status_code": 0,
        "tags": [],
        "thumbnail": "https://a57.foxnews.com/static.foxnews.com/foxnews.com/content/uploads/2024/12/931/523/omer-neutra-dead.jpg?ve=1&tl=1",
        "title": "American-Israeli IDF platoon commander killed in battle, body held in Gaza, IDF says",
        "vote": 0
    },
    {
        "age": null,
        "album": "",
        "author": null,
        "bookmarked": false,
        "comments": [],
        "date_published": "2024-12-02T07:26:28+00:00",
        "description": "Get all the stories you need-to-know from the most powerful name in news delivered first thing every morning to your inbox.",
        "id": 1626260,
        "language": "en-US",
        "link": "https://www.foxnews.com/us/biden-pardons-son-hunter-after-pledging-he-wouldnt-more-top-headlines",
        "manual_status_code": 0,
        "page_rating": 27,
        "page_rating_contents": 86,
        "page_rating_visits": 0,
        "page_rating_votes": 0,
        "permanent": false,
        "source__id": 120,
        "source_url": "https://moxie.foxnews.com/google-publisher/latest.xml",
        "status_code": 0,
        "tags": [],
        "thumbnail": "https://a57.foxnews.com/static.foxnews.com/foxnews.com/content/uploads/2024/12/931/524/hunter-joe-biden.jpg?ve=1&tl=1",
        "title": "Biden pardons son Hunter after pledging that he wouldn\u2019t and more top headlines",
        "vote": 0
    },
    {
        "age": null,
        "album": "",
        "author": null,
        "bookmarked": false,
        "comments": [],
        "date_published": "2024-12-02T06:57:51+00:00",
        "description": "Colorado Gov. Jared Polis is criticizing President Biden&apos;s decision to pardon his son Hunter, saying he is putting &quot;his family ahead of the country.&quot;",
        "id": 1625815,
        "language": "en-US",
        "link": "https://www.foxnews.com/politics/dem-colorado-governor-criticizes-biden-hunter-pardon-put-his-family-ahead-country",
        "manual_status_code": 0,
        "page_rating": 27,
        "page_rating_contents": 86,
        "page_rating_visits": 0,
        "page_rating_votes": 0,
        "permanent": false,
        "source__id": 120,
        "source_url": "https://moxie.foxnews.com/google-publisher/latest.xml",
        "status_code": 0,
        "tags": [],
        "thumbnail": "https://a57.foxnews.com/static.foxnews.com/foxnews.com/content/uploads/2024/12/931/523/biden-polis.jpg?ve=1&tl=1",
        "title": "Dem Colorado governor criticizes Biden for Hunter pardon: 'Put his family ahead of the country'",
        "vote": 0
    },
    {
        "age": null,
        "album": "",
        "author": null,
        "bookmarked": false,
        "comments": [],
        "date_published": "2024-12-02T06:55:20+00:00",
        "description": "Republicans sound off on President Joe Biden&apos;s claim that &quot;no one is above the law&quot; in light of the president&apos;s decision to pardon his son Hunter.",
        "id": 1625816,
        "language": "en-US",
        "link": "https://www.foxnews.com/politics/republicans-react-bidens-no-one-above-law-post-following-hunter-pardon",
        "manual_status_code": 0,
        "page_rating": 27,
        "page_rating_contents": 86,
        "page_rating_visits": 0,
        "page_rating_votes": 0,
        "permanent": false,
        "source__id": 120,
        "source_url": "https://moxie.foxnews.com/google-publisher/latest.xml",
        "status_code": 0,
        "tags": [],
        "thumbnail": "https://a57.foxnews.com/static.foxnews.com/foxnews.com/content/uploads/2024/12/931/523/hunter-joe-biden.jpg?ve=1&tl=1",
        "title": "Republicans hammer Biden's 'No one is above the law' claim following Hunter pardon: 'Aged like fine milk'",
        "vote": 0
    },
    {
        "age": null,
        "album": "",
        "author": null,
        "bookmarked": false,
        "comments": [],
        "date_published": "2024-12-02T06:14:45+00:00",
        "description": "A Houston man has been arrested and charged after allegedly fatally stabbing a mother and her 2-year-old daughter in their apartment Friday.",
        "id": 1625817,
        "language": "en-US",
        "link": "https://www.foxnews.com/us/houston-man-accused-killing-mother-2-year-old-girl-found-sleeping-apartment-dead-victims",
        "manual_status_code": 0,
        "page_rating": 27,
        "page_rating_contents": 86,
        "page_rating_visits": 0,
        "page_rating_votes": 0,
        "permanent": false,
        "source__id": 120,
        "source_url": "https://moxie.foxnews.com/google-publisher/latest.xml",
        "status_code": 0,
        "tags": [],
        "thumbnail": "https://a57.foxnews.com/static.foxnews.com/foxnews.com/content/uploads/2024/12/931/523/kendrick-fisher.jpg?ve=1&tl=1",
        "title": "Houston man accused of killing mother and 2-year-old girl found sleeping in apartment with dead victims",
        "vote": 0
    },
    {
        "age": null,
        "album": "",
        "author": null,
        "bookmarked": false,
        "comments": [],
        "date_published": "2024-12-02T06:00:47+00:00",
        "description": "From 1999 to 2020, the number of alcohol-related deaths has nearly doubled, according to Florida Atlantic University study. A researcher and addiction specialists discuss the risk factors.",
        "id": 1625426,
        "language": "en-US",
        "link": "https://www.foxnews.com/health/alcohol-deaths-have-more-doubled-recent-years-especially-among-women",
        "manual_status_code": 0,
        "page_rating": 27,
        "page_rating_contents": 86,
        "page_rating_visits": 0,
        "page_rating_votes": 0,
        "permanent": false,
        "source__id": 120,
        "source_url": "https://moxie.foxnews.com/google-publisher/latest.xml",
        "status_code": 0,
        "tags": [],
        "thumbnail": "https://a57.foxnews.com/static.foxnews.com/foxnews.com/content/uploads/2021/06/931/523/national-drinking-trends-women_sticok.jpg?ve=1&tl=1",
        "title": "Alcohol deaths have more than doubled in recent years, especially among women",
        "vote": 0
    },
    {
        "age": null,
        "album": "",
        "author": null,
        "bookmarked": false,
        "comments": [],
        "date_published": "2024-12-02T05:30:15+00:00",
        "description": "A suspect charged in the shooting of an Orthodox\u00a0Jewish man as he made his way to a Chicago Synagogue was found dead by suicide in his jail cell.",
        "id": 1625427,
        "language": "en-US",
        "link": "https://www.foxnews.com/us/chicago-suspect-accused-shooting-jewish-man-near-synagogue-dead-after-found-hanging-his-cell",
        "manual_status_code": 0,
        "page_rating": 27,
        "page_rating_contents": 86,
        "page_rating_visits": 0,
        "page_rating_votes": 0,
        "permanent": false,
        "source__id": 120,
        "source_url": "https://moxie.foxnews.com/google-publisher/latest.xml",
        "status_code": 0,
        "tags": [],
        "thumbnail": "https://a57.foxnews.com/static.foxnews.com/foxnews.com/content/uploads/2024/11/931/523/sidi-mohamed-abdallahi.jpg?ve=1&tl=1",
        "title": "Chicago suspect accused of shooting Jewish man near synagogue is dead after found hanging in his cell",
        "vote": 0
    },
    {
        "age": null,
        "album": "",
        "author": null,
        "bookmarked": false,
        "comments": [],
        "date_published": "2024-12-02T05:00:27+00:00",
        "description": "Trump needs to help fix the FAA and to stave off the damage caused by DEI. That means he will need to modernize the operation and cut through the bureaucratic red tape.",
        "id": 1626721,
        "language": "en-US",
        "link": "https://www.foxnews.com/opinion/trump-can-get-faa-take-off-fly-right-direction-amid-democrat-created-dei-storm",
        "manual_status_code": 0,
        "page_rating": 27,
        "page_rating_contents": 86,
        "page_rating_visits": 0,
        "page_rating_votes": 0,
        "permanent": false,
        "source__id": 120,
        "source_url": "https://moxie.foxnews.com/google-publisher/latest.xml",
        "status_code": 0,
        "tags": [],
        "thumbnail": "https://a57.foxnews.com/static.foxnews.com/foxnews.com/content/uploads/2024/07/931/523/Fourth-of-July-travel.jpg?ve=1&tl=1",
        "title": "Trump can get the FAA to take off and fly in the right direction amid a Democrat-created DEI storm",
        "vote": 0
    },
    {
        "age": null,
        "album": "",
        "author": null,
        "bookmarked": false,
        "comments": [],
        "date_published": "2024-12-02T05:00:06+00:00",
        "description": "The Biden-Harris administration went to war with the energy industry on day one. Now that Trump is coming in, America has the power to be great and let our economy soar.",
        "id": 1626722,
        "language": "en-US",
        "link": "https://www.foxnews.com/opinion/trumps-energy-agenda-can-make-america-affordable-again",
        "manual_status_code": 0,
        "page_rating": 27,
        "page_rating_contents": 86,
        "page_rating_visits": 0,
        "page_rating_votes": 0,
        "permanent": false,
        "source__id": 120,
        "source_url": "https://moxie.foxnews.com/google-publisher/latest.xml",
        "status_code": 0,
        "tags": [],
        "thumbnail": "https://a57.foxnews.com/static.foxnews.com/foxnews.com/content/uploads/2023/09/931/523/GettyImages-1477191577.jpg?ve=1&tl=1",
        "title": "Trump\u2019s energy agenda can make America affordable again",
        "vote": 0
    },
    {
        "age": null,
        "album": "",
        "author": null,
        "bookmarked": false,
        "comments": [],
        "date_published": "2024-12-02T05:00:03+00:00",
        "description": "A former butler for King Charles III says the only way a person should eat a hamburger is with a knife and fork. Is that really the case? An etiquette expert weighed in with thoughts.",
        "id": 1625059,
        "language": "en-US",
        "link": "https://www.foxnews.com/food-drink/kings-butler-you-should-eat-burgers-knife-fork",
        "manual_status_code": 0,
        "page_rating": 27,
        "page_rating_contents": 86,
        "page_rating_visits": 0,
        "page_rating_votes": 0,
        "permanent": false,
        "source__id": 120,
        "source_url": "https://moxie.foxnews.com/google-publisher/latest.xml",
        "status_code": 0,
        "tags": [],
        "thumbnail": "https://a57.foxnews.com/static.foxnews.com/foxnews.com/content/uploads/2024/11/931/523/istock-1457646470.jpg?ve=1&tl=1",
        "title": "'I'm the king's butler and I say you should eat burgers with a knife and fork'",
        "vote": 0
    },
    {
        "age": null,
        "album": "",
        "author": null,
        "bookmarked": false,
        "comments": [],
        "date_published": "2024-12-02T04:13:37+00:00",
        "description": "A man wanted in Harris County, Texas, was arrested and charged after an alleged carjacking and killing of a 70-year-old man in Atlanta, Georgia.",
        "id": 1625060,
        "language": "en-US",
        "link": "https://www.foxnews.com/us/fugitive-19-sought-texas-accused-killing-70-year-old-man-georgia-carjacking",
        "manual_status_code": 0,
        "page_rating": 27,
        "page_rating_contents": 86,
        "page_rating_visits": 0,
        "page_rating_votes": 0,
        "permanent": false,
        "source__id": 120,
        "source_url": "https://moxie.foxnews.com/google-publisher/latest.xml",
        "status_code": 0,
        "tags": [],
        "thumbnail": "https://a57.foxnews.com/static.foxnews.com/foxnews.com/content/uploads/2024/12/931/523/mosley.png?ve=1&tl=1",
        "title": "Fugitive, 19, sought in Texas accused of killing 70-year-old man in Georgia carjacking",
        "vote": 0
    },
    {
        "age": null,
        "album": "",
        "author": null,
        "bookmarked": false,
        "comments": [],
        "date_published": "2024-12-02T04:10:46+00:00",
        "description": "Ted Bundy&apos;s former lawyer says the cases against his client and University of Idaho student murders suspect Bryan Kohberger share the same key misstep.",
        "id": 1625061,
        "language": "en-US",
        "link": "https://www.foxnews.com/us/ted-bundy-lawyer-reveals-what-totally-fascinates-him-about-bryan-kohberger-case",
        "manual_status_code": 0,
        "page_rating": 27,
        "page_rating_contents": 86,
        "page_rating_visits": 0,
        "page_rating_votes": 0,
        "permanent": false,
        "source__id": 120,
        "source_url": "https://moxie.foxnews.com/google-publisher/latest.xml",
        "status_code": 0,
        "tags": [],
        "thumbnail": "https://a57.foxnews.com/static.foxnews.com/foxnews.com/content/uploads/2024/11/931/523/bundy-kohberger-split.png?ve=1&tl=1",
        "title": "Ted Bundy lawyer reveals what 'totally fascinates' him about Bryan Kohberger case",
        "vote": 0
    },
    {
        "age": null,
        "album": "",
        "author": null,
        "bookmarked": false,
        "comments": [],
        "date_published": "2024-12-02T04:00:49+00:00",
        "description": "There were a handful of upsets during the college football weekend. But no one will be talking about that as flag fights marred the interesting slate of matchups.",
        "id": 1625062,
        "language": "en-US",
        "link": "https://www.foxnews.com/sports/fox-news-digital-sports-college-football-winners-losers-week-14",
        "manual_status_code": 0,
        "page_rating": 27,
        "page_rating_contents": 86,
        "page_rating_visits": 0,
        "page_rating_votes": 0,
        "permanent": false,
        "source__id": 120,
        "source_url": "https://moxie.foxnews.com/google-publisher/latest.xml",
        "status_code": 0,
        "tags": [],
        "thumbnail": "https://a57.foxnews.com/static.foxnews.com/foxnews.com/content/uploads/2024/12/931/523/ryan-day.jpg?ve=1&tl=1",
        "title": "Fox News Digital Sports' college football winners and losers: Week 14",
        "vote": 0
    },
    {
        "age": null,
        "album": "",
        "author": null,
        "bookmarked": false,
        "comments": [],
        "date_published": "2024-12-02T04:00:38+00:00",
        "description": "In Latin America, leaders are reacting in different ways to Trump&apos;s victory. Right-wing governments are optimistic about the future policies while socialists fear measures that would affect their authoritarian projects",
        "id": 1625818,
        "language": "en-US",
        "link": "https://www.foxnews.com/world/trump-victory-boosts-conservatives-latin-america-wake-up-call-dictators-there-consequences",
        "manual_status_code": 0,
        "page_rating": 27,
        "page_rating_contents": 86,
        "page_rating_visits": 0,
        "page_rating_votes": 0,
        "permanent": false,
        "source__id": 120,
        "source_url": "https://moxie.foxnews.com/google-publisher/latest.xml",
        "status_code": 0,
        "tags": [],
        "thumbnail": "https://a57.foxnews.com/static.foxnews.com/foxnews.com/content/uploads/2024/11/931/523/milei-trump-maduro-split-photo-1.jpg?ve=1&tl=1",
        "title": "Trump victory boosts conservatives in Latin America, wake-up call to dictators: 'there will be consequences'",
        "vote": 0
    },
    {
        "age": null,
        "album": "",
        "author": null,
        "bookmarked": false,
        "comments": [],
        "date_published": "2024-12-02T04:00:23+00:00",
        "description": "Travelers sitting in a certain row on a plane must confirm that he or she is willing and able to assist in the event of an emergency. Here&apos;s what else you need to know.",
        "id": 1625063,
        "language": "en-US",
        "link": "https://www.foxnews.com/travel/flight-passengers-sitting-row-must-pass-certain-requirements-what-know",
        "manual_status_code": 0,
        "page_rating": 27,
        "page_rating_contents": 86,
        "page_rating_visits": 0,
        "page_rating_votes": 0,
        "permanent": false,
        "source__id": 120,
        "source_url": "https://moxie.foxnews.com/google-publisher/latest.xml",
        "status_code": 0,
        "tags": [],
        "thumbnail": "https://a57.foxnews.com/static.foxnews.com/foxnews.com/content/uploads/2024/11/931/523/istock-1277665856.jpg?ve=1&tl=1",
        "title": "Flight passengers sitting in this row must pass certain requirements: What to know",
        "vote": 0
    },
    {
        "age": null,
        "album": "",
        "author": null,
        "bookmarked": false,
        "comments": [],
        "date_published": "2024-12-02T04:00:20+00:00",
        "description": "A former FBI special agent details what she wants to see happen if Kash Patel is confirmed as the agency&apos;s new director. President-elect Trump tapped Patel for the job.",
        "id": 1625064,
        "language": "en-US",
        "link": "https://www.foxnews.com/us/trump-fbi-pick-kash-patel-should-take-concrete-steps-restore-trust-former-special-agent",
        "manual_status_code": 0,
        "page_rating": 27,
        "page_rating_contents": 86,
        "page_rating_visits": 0,
        "page_rating_votes": 0,
        "permanent": false,
        "source__id": 120,
        "source_url": "https://moxie.foxnews.com/google-publisher/latest.xml",
        "status_code": 0,
        "tags": [],
        "thumbnail": "https://a57.foxnews.com/static.foxnews.com/foxnews.com/content/uploads/2024/12/931/523/parker-patel.jpg?ve=1&tl=1",
        "title": "Trump FBI pick Kash Patel should take these concrete steps to restore trust: former special agent",
        "vote": 0
    },
    {
        "age": null,
        "album": "",
        "author": null,
        "bookmarked": false,
        "comments": [],
        "date_published": "2024-12-02T04:00:02+00:00",
        "description": "President Biden visits Angola this week and is spending billions to get better supplies of electric vehicle battery metals, but the admin may have already been beaten by China&apos;s investments.",
        "id": 1625819,
        "language": "en-US",
        "link": "https://www.foxnews.com/world/biden-travels-africa-where-policies-were-over-promised-under-delivered-amid-massive-china-expansion",
        "manual_status_code": 0,
        "page_rating": 27,
        "page_rating_contents": 86,
        "page_rating_visits": 0,
        "page_rating_votes": 0,
        "permanent": false,
        "source__id": 120,
        "source_url": "https://moxie.foxnews.com/google-publisher/latest.xml",
        "status_code": 0,
        "tags": [],
        "thumbnail": "https://a57.foxnews.com/static.foxnews.com/foxnews.com/content/uploads/2024/12/931/523/ap22349812610108-scaled.jpg?ve=1&tl=1",
        "title": "Biden travels to Africa where policies were \u2018over-promised and under-delivered,' amid massive China expansion",
        "vote": 0
    },
    {
        "age": null,
        "album": "",
        "author": null,
        "bookmarked": false,
        "comments": [],
        "date_published": "2024-12-02T03:49:18+00:00",
        "description": "A seven-year-old Ohio girl pleaded with her father not to kill her as he threatened to kill her and himself during a standoff with police before he was shot by law enforcement.",
        "id": 1624782,
        "language": "en-US",
        "link": "https://www.foxnews.com/us/ohio-girl-7-begged-her-dad-not-kill-her-after-murder-suicide-threat-i-dont-want-go-heaven-today",
        "manual_status_code": 0,
        "page_rating": 27,
        "page_rating_contents": 86,
        "page_rating_visits": 0,
        "page_rating_votes": 0,
        "permanent": false,
        "source__id": 120,
        "source_url": "https://moxie.foxnews.com/google-publisher/latest.xml",
        "status_code": 0,
        "tags": [],
        "thumbnail": "https://a57.foxnews.com/static.foxnews.com/foxnews.com/content/uploads/2024/12/931/523/alexander.png?ve=1&tl=1",
        "title": "Ohio girl, 7, begged her dad not to kill her after murder-suicide threat: 'I don't want to go to heaven today'",
        "vote": 0
    },
    {
        "age": null,
        "album": "",
        "author": null,
        "bookmarked": false,
        "comments": [],
        "date_published": "2024-12-02T01:10:19+00:00",
        "description": "Hunter Biden said after his father, President Joe Biden, pardoned him that his mistakes have been &quot;exploited to publicly humiliate and shame me and my family for political sport.&quot;",
        "id": 1624393,
        "language": "en-US",
        "link": "https://www.foxnews.com/politics/hunter-biden-says-he-never-take-his-clemency-granted-after-receiving-pardon-from-his-father",
        "manual_status_code": 0,
        "page_rating": 27,
        "page_rating_contents": 86,
        "page_rating_visits": 0,
        "page_rating_votes": 0,
        "permanent": false,
        "source__id": 120,
        "source_url": "https://moxie.foxnews.com/google-publisher/latest.xml",
        "status_code": 0,
        "tags": [],
        "thumbnail": "https://a57.foxnews.com/static.foxnews.com/foxnews.com/content/uploads/2024/12/931/523/hunter-biden.jpg?ve=1&tl=1",
        "title": "Hunter Biden says his mistakes were 'exploited' for political sport, he will never take pardon for granted",
        "vote": 0
    }
]