[{"tags": [], "vote": 0, "age": null, "language": null, "bookmarked": false, "permanent": false, "page_rating": 0, "comments": [], "source": "https://www.youtube.com/feeds/videos.xml?channel_id=UCL_f53ZEJxp8TtlOkHwMV9Q", "date_published": "2024-01-24T16:32:08+00:00", "page_rating_contents": 0, "user": null, "link": "https://www.youtube.com/watch?v=_nw_O1I7ptM", "page_rating_votes": 0, "title": "What Lesson Am I Supposed To Learn?", "page_rating_visits": 0, "description": "Dr. Peterson's extensive catalog is available now on DailyWire+: https://bit.ly/3KrWbS8\n\n// LINKS //\nAll links: https://linktr.ee/drjordanbpeterson\nWebsite: https://jordanbpeterson.com\nTour Locations: https://jordanbpeterson.com/events\nX: https://twitter.com/jordanbpeterson\nInstagram: https://instagram.com/jordan.b.peterson\nFacebook: https://facebook.com/drjordanpeterson\nTelegram: https://t.me/DrJordanPeterson\nNewsletter: https://mailchi.mp/jordanbpeterson.com/youtubesignup\n\n// COURSES //\nDiscovering Personality: https://jordanbpeterson.com/personality\nSelf Authoring Suite: https://selfauthoring.com\nUnderstand Myself (personality test): https://understandmyself.com\n\n// BOOKS //\nBeyond Order: 12 More Rules for Life: https://jordanbpeterson.com/Beyond-Order\n12 Rules for Life: An Antidote to Chaos: https://jordanbpeterson.com/12-rules-for-life\nMaps of Meaning: The Architecture of Belief: https://jordanbpeterson.com/maps-of-meaning\n\n#JordanPeterson #JordanBPeterson #DrJordanPeter", "artist": "Jordan B Peterson", "source_obj__id": 93, "thumbnail": "https://i4.ytimg.com/vi/_nw_O1I7ptM/hqdefault.jpg", "album": "", "dead": false}]